LICENSE
segmed/__init__.py
segmed/metrics/__init__.py
segmed/metrics/losses.py
segmed/metrics/metrics.py
segmed/models/__init__.py
segmed/models/multiresunet.py
segmed/models/segmodel.py
segmed/models/unet.py
segmed/train/__init__.py
segmed/train/train_segnet.py
segmed/train/train_unet.py
segmed/utils/__init__.py
segmed/utils/timing.py
segmed/utils/utils.py
segmed-0.6.12.dist-info/LICENSE
segmed-0.6.12.dist-info/WHEEL
segmed-0.6.12.dist-info/METADATA
segmed-0.6.12.dist-info/RECORD
