Metadata-Version: 2.1
Name: segmed
Version: 0.6.12
Summary: Applying Deep Learning to medical image segmentation tasks
Home-page: https://github.com/DCI-NET/segmed
License: MIT
Author: Edwin Bedolla
Author-email: developeredwin@gmail.com
Requires-Python: >=3.7,<4.0
Classifier: License :: OSI Approved :: MIT License
Classifier: Programming Language :: Python :: 3
Classifier: Programming Language :: Python :: 3.7
Requires-Dist: scikit-image (>=0.16.2,<0.17.0)
Requires-Dist: scikit-learn (>=0.21.3,<0.22.0)
Requires-Dist: tensorflow (>=2.0,<3.0)
Project-URL: Repository, https://github.com/DCI-NET/segmed
